crtmlib/__init__.py
crtmlib/crtmlib.py
crtmlib-0.1.1.dist-info/METADATA
crtmlib-0.1.1.dist-info/WHEEL
crtmlib-0.1.1.dist-info/top_level.txt
crtmlib-0.1.1.dist-info/RECORD
